{
  "version": 1,
  "base_track": "完璧主義で☆",
  "base_artist": "FRUITS ZIPPER",
  "createdAt": "2026-01-04T03:45:35.959152Z",
  "candidates": [
    {
      "id": "lrclib_1",
      "source": "lrclib",
      "title": "完璧主義で☆",
      "artist": "FRUITS ZIPPER",
      "has_synced": true,
      "path": "select/01_完璧主義で☆_FRUITS_ZIPPER.lrc"
    },
    {
      "id": "petitlyrics_1",
      "source": "petitlyrics",
      "title": "完璧主義で☆",
      "artist": "FRUITS ZIPPER",
      "has_synced": false,
      "path": "select/pl_01_完璧主義で☆_FRUITS_ZIPPER.txt"
    }
  ]
}